{
    "items": [{
    	"key": "intro_text",
    	"value": "Inicializando corteza robótica...\nTemperatura del reactor en condiciones óptimas...\nComputadora en línea...\nEscudo de iones energizado...\nMecanismos automáticos activos...\nRobot tipo Luciérnaga en rango..."
    }, {
    	"key": "intro_skip",
    	"value": "Clic para omitir"
	}, {
		"key": "click_to_start",
    	"value": "Clic para iniciar"
    }, {
    	"key": "start_game",
    	"value": "Inicio Juego"
    }, {
    	"key": "level_select",
    	"value": "Seleccione nivel"
    }, {
    	"key": "how_to_play",
    	"value": "Cómo jugar"
    }, {
    	"key": "options",
    	"value": "Opciones"
    }, {
    	"key": "credits",
    	"value": "Créditos"
    }, {
    	"key": "make_games",
    	"value": "Diseña tus juegos"
    }, {
    	"key": "language_select",
    	"value": "Idioma"
    }, {
    	"key": "master_volume",
    	"value": "Volumen principal"
    }, {
    	"key": "effects_volume",
    	"value": "Volumen de efectos"
    }, {
    	"key": "music_volume",
    	"value": "Volumen de la música"
    }, {
    	"key": "back_button",
    	"value": "Volver"
    }, {
    	"key": "reset_progress",
    	"value": "Reiniciar"
    }, {
    	"key": "cleared_level",
    	"value": "Completado"
    }, {
    	"key": "city",
    	"value": "la Ciudad"
    }, {
    	"key": "space_station",
    	"value": "la estación espacial"
    }, {
    	"key": "enemy_base",
    	"value": "la base enemiga"
    }, {
    	"key": "controls",
    	"value": "Mover - [WASD] o teclas de [dirección]\nVolar - [Arriba] o [Barra espaciadora]\nApuntar - [Ratón]\nArma primaria - [Botón izquierdo del ratón]\nArma secundaria - [Botón derecho del ratón]\nEntrar / Salir del robot - [E]\nPausar el juego - [Escape]\nDisparar lanzador - [Q]\nEscudo - [Mayúscula izquierda]"
    }, {
    	"key": "mission_details_title",
    	"value": "Detalles de la misión"
    }, {
    	"key": "back_to_main_menu",
    	"value": "Regresar al menú principal"
    }, {
    	"key": "continue",
    	"value": "Continuar"
    }, {
    	"key": "mission_details_text",
    	"value": "Bienvenido a Caballería de Acero, soldado. ¡Te has graduado entre los primeros de tu clase en la Academia de pilotos y hoy realizarás tu primera misión! Unos piratas espaciales han ocupado parte de la ciudad y han tomado rehenes para pedir rescate. Limpia el área y distráelos mientras otro equipo ayuda a rescatar a los rehenes."
    }]
}